iam_json_lint/__init__.py
iam_json_lint/cli.py
iam_json_lint/linter.py
iam_json_lint/validator.py
iam_json_lint-0.2.0.data/data/iam_json_lint/config_override.yaml
iam_json_lint-0.2.0.dist-info/METADATA
iam_json_lint-0.2.0.dist-info/WHEEL
iam_json_lint-0.2.0.dist-info/entry_points.txt
iam_json_lint-0.2.0.dist-info/licenses/LICENSE
iam_json_lint-0.2.0.dist-info/RECORD
